.gitlab-ci.yml
.readthedocs.yaml
COPYING
MANIFEST.in
NEWS
PKG-INFO.in
README.rst
meson.build
meson_options.txt
pygobject-3.0.pc.in
pygobject.doap
pyproject.toml
setup.cfg
setup.py
.gitlab-ci/Dockerfile
.gitlab-ci/Dockerfile.old
.gitlab-ci/README.rst
.gitlab-ci/coverage-docker.sh
.gitlab-ci/fixup-covpy-paths.py
.gitlab-ci/fixup-lcov-paths.py
.gitlab-ci/lcovrc
.gitlab-ci/run-docker-old.sh
.gitlab-ci/run-docker-runtime.sh
.gitlab-ci/run-docker.sh
.gitlab-ci/test-docker-old.sh
.gitlab-ci/test-docker.sh
.gitlab-ci/test-flatpak-gtk4.sh
.gitlab-ci/test-flatpak.sh
.gitlab-ci/test-msys2.sh
PyGObject.egg-info/PKG-INFO
PyGObject.egg-info/SOURCES.txt
PyGObject.egg-info/dependency_links.txt
PyGObject.egg-info/not-zip-safe
PyGObject.egg-info/requires.txt
PyGObject.egg-info/top_level.txt
docs/Makefile
docs/bugs_repo.rst
docs/changelog.rst
docs/conf.py
docs/contact.rst
docs/extra.css
docs/further.rst
docs/getting_started.rst
docs/icons.rst
docs/index.rst
docs/maintguide.rst
docs/packagingguide.rst
docs/requirements.txt
docs/devguide/building_testing.rst
docs/devguide/dev_environ.rst
docs/devguide/index.rst
docs/devguide/override_guidelines.rst
docs/devguide/overview.rst
docs/devguide/style_guide.rst
docs/guide/cairo_integration.rst
docs/guide/debug_profile.rst
docs/guide/deploy.rst
docs/guide/faq.rst
docs/guide/gtk_template.rst
docs/guide/index.rst
docs/guide/porting.rst
docs/guide/testing.rst
docs/guide/threading.rst
docs/guide/api/api.rst
docs/guide/api/basic_types.rst
docs/guide/api/error_handling.rst
docs/guide/api/flags_enums.rst
docs/guide/api/gobject.rst
docs/guide/api/index.rst
docs/guide/api/properties.rst
docs/guide/api/signals.rst
docs/guide/api/weakrefs.rst
docs/guide/code/cairo-demo.py
docs/guide/images/cairo_integration.png
docs/images/LICENSE
docs/images/favicon.ico
docs/images/logo.svg
docs/images/overview.dia
docs/images/overview.svg
docs/images/pygobject-small.svg
docs/images/pygobject.svg
docs/images/start_linux.png
docs/images/start_macos.png
docs/images/start_windows.png
examples/cairo-demo.py
examples/option.py
examples/properties.py
examples/signal.py
examples/demo/demo.py
examples/demo/demos/__init__.py
examples/demo/demos/appwindow.py
